{
  "Example1 - Plant_gene_expression_RPKM.txt":
    {"link":"",
      "annotation_file":"example/gene_annotations.txt",
      "description":"example1_description.php",
      "images":
        {
          "Leaf":"leaf.jpeg",
          "Fruit":"fruit.jpeg",
          "Root":"root.jpeg",
          "Peel":"peel.jpeg",
          "Seed":"seed.jpeg",
          "Germinating Seed":"germinating_seed.jpeg",
          "Darkness":"darkness.jpeg",
          "Drought":"drought.jpeg",
          "Heat":"heat.jpeg",
          "Cold":"cold.jpeg"
        }
    },
  "Example2 - Organism dataset name.txt":
    {"link":"#",
      "description":"example2_description.php"
    },
  "Example3 - Dataset with cartoons.txt":
    {
      "link":"",
      "annotation_file":"example/gene_annotations.txt",
      "cartoons":"cartoons_example1.json"
    }
}
